virtenv.py
virtenv_cli.py
virtenv-0.3.1.dist-info/METADATA
virtenv-0.3.1.dist-info/RECORD
virtenv-0.3.1.dist-info/WHEEL
virtenv-0.3.1.dist-info/entry_points.txt
virtenv-0.3.1.dist-info/top_level.txt
