Metadata-Version: 1.2
Name: virtenv
Version: 0.3.1
Summary: Create a virtual environment with venv or virtualenv
Home-page: https://github.com/sarugaku/virtenv
Author: Tzu-ping Chung
Author-email: uranusjr@gmail.com
License: ISC License
Keywords: venv,virtualenv
Platform: UNKNOWN
Classifier: Development Status :: 4 - Beta
Classifier: Intended Audience :: Developers
Classifier: License :: OSI Approved :: ISC License (ISCL)
Classifier: Operating System :: OS Independent
Classifier: Programming Language :: Python :: 2
Classifier: Programming Language :: Python :: 2.7
Classifier: Programming Language :: Python :: 3
Classifier: Programming Language :: Python :: 3.4
Classifier: Programming Language :: Python :: 3.5
Classifier: Programming Language :: Python :: 3.6
Classifier: Programming Language :: Python :: 3.7
Requires-Python: >=2.7,!=3.0,!=3.1,!=3.2,!=3.3
